geqco/__init__.py
geqco/example.py
geqco-0.1.0.dist-info/WHEEL
geqco-0.1.0.dist-info/METADATA
geqco-0.1.0.dist-info/RECORD
