Metadata-Version: 2.1
Name: geqco
Version: 0.1.0
Summary: A brief description of your package
Author: Aron Jansen
Author-email: aronpjansen@gmail.com
Requires-Python: >=3.9,<4.0
Classifier: Programming Language :: Python :: 3
Classifier: Programming Language :: Python :: 3.9
Classifier: Programming Language :: Python :: 3.10
